MANIFEST.in
README
setup.py
worktime/__init__.py
worktime/worktime.py
worktime.egg-info/PKG-INFO
worktime.egg-info/SOURCES.txt
worktime.egg-info/dependency_links.txt
worktime.egg-info/entry_points.txt
worktime.egg-info/top_level.txt
worktime/templates/default-contents.xhtml
worktime/templates/default-print.css
worktime/templates/default.css
worktime/templates/default.xhtml
worktime/templates/footer.xhtml