Metadata-Version: 1.0
Name: worktime
Version: 0.3
Summary: Generate XHTML daily calendar
Home-page: http://github.com/l0b0/worktime
Author: Victor Engmark
Author-email: victor.engmark@gmail.com
License: GPL v3 or newer
Download-URL: http://github.com/l0b0/worktime
Keywords: log calendar generator
Platform: POSIX
Platform: Windows
Classifier: Development Status :: 3 - Alpha
Classifier: Environment :: Console
Classifier: Intended Audience :: End Users/Desktop
Classifier: License :: OSI Approved :: GNU General Public License (GPL)
Classifier: Natural Language :: English
Classifier: Operating System :: OS Independent
Classifier: Programming Language :: Python :: 2.6
Classifier: Topic :: Office/Business
Classifier: Topic :: Other/Nonlisted Topic
